{
    "Attributes": {
        "Mental_Attributes": {
            "Intelligence": 3,
            "Resolve": 5,
            "Wits": 1
        },
        "Physical_Attributes": {
            "Dexterity": 2,
            "Stamina": 2,
            "Strength": 4
        },
        "Social_Attributes": {
            "Charisma": 5,
            "Composure": 1,
            "Manipulation": 3
        }
    },
    "Character_Details": {
        "Basic_Information": {
            "Age": 299,
            "Clan": "Malkavian",
            "Derangement": [
                "Disorientation: Commonly associated with Celerity, the vampire finds the way things move in normal speed disorienting, insisting that they should move slower.[34]"
            ],
            "Generation": 14,
            "Name": "Brittney, Florentine",
            "Sex": "Female",
            "Sire": "Older Vampire"
        },
        "Trackers": {
            "Blood_Potency": 0,
            "Health": 5,
            "Willpower": 6,
            "XP_Left": 0
        }
    },
    "Disciplines": {
        "Clan_Disciplines": {
            "Auspex": {
                "Level": 3,
                "Skills": {
                    "": "",
                    "Heightened Senses": " The vampire can add their Auspex rating to their perception checks.",
                    "Premonition": " The vampire can receive visions and hints about what is about to happen.",
                    "Sense the Unseen": " The vampire can detect things that are supernaturally invisible",
                    "Share the Senses": " The vampire can sense through the senses of another kindred or mortal."
                }
            },
            "Dominate": {
                "Level": 1,
                "Skills": {
                    "": "",
                    "Cloud Memory": "The vampire can make the target forget the past few minutes."
                }
            }
        },
        "Non-Clan_Disciplines": {
            "Animalism": {
                "Level": 1,
                "Skills": {
                    "": "",
                    "Bound Famulus": "The vampire can form a bond with an animal facilitating the use of other Animalism powers."
                }
            },
            "Blood_Sorcery": {
                "Level": 1,
                "Skills": {
                    "": "",
                    "A Taste for Blood": "By tasting a drop of blood, the user can discern certain basic traits of the one to whom it belongs"
                }
            },
            "Fortitude": {
                "Level": 1,
                "Skills": {
                    "": "",
                    "Unswayable Mind": "The vampire can add their Fortitude rating to dice rolls to resist manipulation and coercion."
                }
            },
            "Oblivion": {
                "Level": 1,
                "Skills": {
                    "": "",
                    "The Binding Fetter": "The vampire can identify objects and locations important to ghosts by a faint aura."
                }
            },
            "Potence": {
                "Level": 1,
                "Skills": {
                    "": "",
                    "Soaring Leap": "The Kindred can leap higher and further."
                }
            },
            "Presence": {
                "Level": 2,
                "Skills": {
                    "": "",
                    "Awe": "The vampire can add their Presence rating to their Persuasion and Performance checks",
                    "Lingering Kiss": "The vampire can gain bonuses to their Social pools against targets that they have Kissed."
                }
            }
        }
    },
    "Skills": {
        "Mental_Skills": {
            "Academics": 1,
            "Awareness": 0,
            "Finance": 2,
            "Investigation": 0,
            "Medicine": 1,
            "Occult": 0,
            "Politics": 2,
            "Science": 0,
            "Technology": 1
        },
        "Physical_Skills": {
            "Athletics": 0,
            "Brawl": 0,
            "Craft": 4,
            "Drive": 1,
            "Firearms": 1,
            "Larceny": 1,
            "Melee": 1,
            "Stealth": 0,
            "Survival": 0
        },
        "Social_Skills": {
            "Animal Ken": 0,
            "Etiquette": 0,
            "Insight": 0,
            "Intimidation": 1,
            "Leadership": 0,
            "Performance": 2,
            "Persuasion": 1,
            "Streetwise": 0,
            "Subterfuge": 0
        }
    }
}